distbackup/__init__.py
distbackup/__main__.py
distbackup/backup.py
distbackup/cli.py
distbackup/constants.py
distbackup/database.py
distbackup/disk.py
distbackup/errors.py
distbackup/logger.py
distbackup/nexus.py
distbackup/objects.py
distbackup/report.py
distbackup/restore.py
distbackup/schema.py
distbackup/sourcefile.py
distbackup/update.py
distbackup/utils.py
distbackup/verify.py
distbackup-1.0.20.dist-info/LICENSE
distbackup-1.0.20.dist-info/METADATA
distbackup-1.0.20.dist-info/WHEEL
distbackup-1.0.20.dist-info/entry_points.txt
distbackup-1.0.20.dist-info/top_level.txt
distbackup-1.0.20.dist-info/RECORD
